py_tel_reverse_shell/Engine.py
py_tel_reverse_shell/__init__.py
py_tel_reverse_shell/tel_shell.py
py_tel_reverse_shell/tools.py
Telegram_reverse_shell_lib-0.1.dist-info/LICENSE
Telegram_reverse_shell_lib-0.1.dist-info/METADATA
Telegram_reverse_shell_lib-0.1.dist-info/WHEEL
Telegram_reverse_shell_lib-0.1.dist-info/top_level.txt
Telegram_reverse_shell_lib-0.1.dist-info/RECORD
